{
  "packets":{
    "actorList":["0-1931"],
    "ai":[],
    "cellChangeFrom":[],
    "cellChangeTo":[],
    "container":["0-1931"],
    "death":[],
    "delete":[],
    "doorState":[],
    "equipment":[],
    "lock":[],
    "place":[],
    "position":["0-1931"],
    "scale":[],
    "spawn":["0-1931"],
    "state":[],
    "statsDynamic":["0-1931"],
    "trap":[],
    "spellsActive":[],
    "miscellaneous":[],
    "clientScriptLocal":[]
  },
  "entry":{
    "creationTime":1697217737,
    "description":"-6, 16"
  },
  "lastVisit":{
    "ZIR":1697455515,
    "Adamast":1697219228,
    "Violetta":1697455518
  },
  "recordLinks":[],
  "objectData":{
    "0-1931":{
      "refId":"scrib",
      "location":{
        "posX":-45547.875,
        "posZ":1075.5505371094,
        "posY":135955.9375,
        "rotX":0.055626440793276,
        "rotY":0,
        "rotZ":-0.96213889122009
      },
      "stats":{
        "healthCurrent":8,
        "magickaCurrent":12,
        "healthModified":8,
        "fatigueBase":300,
        "fatigueModified":300,
        "healthBase":8,
        "magickaModified":12,
        "magickaBase":12,
        "fatigueCurrent":300
      },
      "inventory":[{
          "refId":"ingred_scrib_jelly_01",
          "count":1,
          "charge":-1,
          "enchantmentCharge":-1,
          "soul":""
        }]
    }
  },
  "loadState":{
    "hasFullContainerData":true,
    "hasFullActorList":true
  }
}