{
  "packets":{
    "actorList":["193099-0","193097-0"],
    "ai":[],
    "cellChangeFrom":[],
    "cellChangeTo":[],
    "container":["193118-0","193119-0","193097-0","193099-0"],
    "death":[],
    "delete":["193050-0","193051-0","193052-0","193105-0","193072-0"],
    "doorState":["193002-0","193001-0","193006-0","193004-0","193081-0","193080-0"],
    "equipment":["193099-0","193097-0"],
    "lock":[],
    "place":[],
    "position":["193097-0","193099-0"],
    "scale":[],
    "spawn":[],
    "state":[],
    "statsDynamic":["193097-0","193099-0"],
    "trap":[],
    "spellsActive":[],
    "miscellaneous":["193097-0","193099-0"],
    "clientScriptLocal":[]
  },
  "entry":{
    "creationTime":1696789632,
    "description":"Nchuleftingth, Upper Levels"
  },
  "lastVisit":{
    "ZIR":1696790933,
    "Adamast":1696790442,
    "Violetta":1696790934
  },
  "recordLinks":[],
  "objectData":{
    "193006-0":{
      "refId":"door_dwrv_inner00",
      "doorState":1
    },
    "193099-0":{
      "refId":"pania cadiusus",
      "location":{
        "posX":2091.6811523438,
        "posZ":-191,
        "posY":266.45379638672,
        "rotX":0,
        "rotY":0,
        "rotZ":-0.97316384315491
      },
      "stats":{
        "healthCurrent":81,
        "magickaCurrent":102,
        "healthModified":81,
        "fatigueBase":183,
        "fatigueModified":183,
        "healthBase":81,
        "magickaModified":102,
        "magickaBase":102,
        "fatigueCurrent":183
      },
      "equipment":{
        "7":{
          "refId":"expensive_shoes_03",
          "count":1,
          "charge":-1,
          "enchantmentCharge":-1
        },
        "8":{
          "refId":"expensive_shirt_03",
          "count":1,
          "charge":-1,
          "enchantmentCharge":-1
        },
        "10":{
          "refId":"expensive_skirt_03",
          "count":1,
          "charge":-1,
          "enchantmentCharge":-1
        },
        "15":{
          "refId":"expensive_belt_03",
          "count":1,
          "charge":-1,
          "enchantmentCharge":-1
        }
      },
      "inventory":[{
          "refId":"expensive_skirt_03",
          "count":1,
          "charge":-1,
          "enchantmentCharge":-1,
          "soul":""
        },{
          "refId":"expensive_belt_03",
          "count":1,
          "charge":-1,
          "enchantmentCharge":-1,
          "soul":""
        },{
          "refId":"expensive_shirt_03",
          "count":1,
          "charge":-1,
          "enchantmentCharge":-1,
          "soul":""
        },{
          "refId":"expensive_shoes_03",
          "count":1,
          "charge":-1,
          "enchantmentCharge":-1,
          "soul":""
        }],
      "lastGoldRestockDay":26,
      "lastGoldRestockHour":13.523403167725,
      "goldPool":0
    },
    "193050-0":{
      "refId":"misc_dwrv_coin00"
    },
    "193080-0":{
      "refId":"door_dwrv_inner00",
      "doorState":1
    },
    "193051-0":{
      "refId":"misc_dwrv_coin00"
    },
    "193072-0":{
      "refId":"misc_dwrv_gear00"
    },
    "193119-0":{
      "refId":"com_sack_01_chpfood5",
      "inventory":[{
          "refId":"ingred_saltrice_01",
          "count":5,
          "charge":-1,
          "enchantmentCharge":-1,
          "soul":""
        }]
    },
    "193118-0":{
      "refId":"com_sack_01_chpfood5",
      "inventory":[{
          "refId":"ingred_scuttle_01",
          "count":5,
          "charge":-1,
          "enchantmentCharge":-1,
          "soul":""
        }]
    },
    "193097-0":{
      "refId":"senilias cadiusus",
      "location":{
        "posX":2213.8515625,
        "posZ":-191,
        "posY":483.79025268555,
        "rotX":0,
        "rotY":0,
        "rotZ":1.5039284229279
      },
      "stats":{
        "healthCurrent":85,
        "magickaCurrent":140,
        "healthModified":85,
        "fatigueBase":227,
        "fatigueModified":227,
        "healthBase":85,
        "magickaModified":140,
        "magickaBase":140,
        "fatigueCurrent":227
      },
      "equipment":{
        "7":{
          "refId":"common_shoes_05",
          "count":1,
          "charge":-1,
          "enchantmentCharge":-1
        },
        "16":{
          "refId":"glass dagger",
          "count":1,
          "charge":-1,
          "enchantmentCharge":-1
        },
        "11":{
          "refId":"common_robe_05_c",
          "count":1,
          "charge":-1,
          "enchantmentCharge":-1
        }
      },
      "inventory":[{
          "refId":"common_robe_05_c",
          "count":1,
          "charge":-1,
          "enchantmentCharge":-1,
          "soul":""
        },{
          "refId":"common_shoes_05",
          "count":1,
          "charge":-1,
          "enchantmentCharge":-1,
          "soul":""
        },{
          "refId":"gold_001",
          "count":15,
          "charge":-1,
          "enchantmentCharge":-1,
          "soul":""
        },{
          "refId":"glass dagger",
          "count":1,
          "charge":-1,
          "enchantmentCharge":-1,
          "soul":""
        }],
      "goldPool":0,
      "lastGoldRestockHour":11.238737106323,
      "lastGoldRestockDay":26
    },
    "193001-0":{
      "refId":"door_dwrv_inner00",
      "doorState":1
    },
    "193052-0":{
      "refId":"misc_dwrv_coin00"
    },
    "193002-0":{
      "refId":"door_dwrv_inner00",
      "doorState":1
    },
    "193081-0":{
      "refId":"door_dwrv_inner00",
      "doorState":1
    },
    "193105-0":{
      "refId":"misc_dwrv_artifact50"
    },
    "193004-0":{
      "refId":"door_dwrv_inner00",
      "doorState":1
    }
  },
  "loadState":{
    "hasFullContainerData":true,
    "hasFullActorList":true
  }
}